[
  {
    "_firebase_id": "mjbgk9j7-15afqh8stiz",
    "boarding_permit_by": "mjbgk5pl-7lrvnqwbbd5",
    "boarding_permit_time": "2025-12-18T09:40:21.763Z",
    "created_at": "2025-12-18T09:10:21.763Z",
    "current_status": "cancelled",
    "departure_order_by": "mjbgk5pl-7lrvnqwbbd5",
    "departure_order_shift_id": "mjbgk8rq-frkuzzav2ld",
    "departure_order_time": "2025-12-18T10:05:21.763Z",
    "driver_full_name": "Nguyễn Văn Tài",
    "driver_id": "mjbgk6zs-fj0x22xt4yc",
    "entry_by": "mjbgk5pl-7lrvnqwbbd5",
    "entry_shift_id": "mjbgk8rq-frkuzzav2ld",
    "entry_time": "2025-12-18T09:10:21.763Z",
    "exit_by": "mjbgk5pl-7lrvnqwbbd5",
    "exit_shift_id": "mjbgk8rq-frkuzzav2ld",
    "exit_time": "2025-12-18T10:10:21.763Z",
    "id": "mjbgk9j7-15afqh8stiz",
    "invoice_number": "HD-001",
    "metadata": {
      "cancellation_reason": "test",
      "cancelled_at": "2025-12-23T08:24:44.219Z",
      "cancelled_by": "mjbgk5pl-cdj0zugj29a",
      "cancelled_by_name": "System Administrator",
      "previous_status": "departed"
    },
    "passenger_drop_by": "mjbgk5pl-7lrvnqwbbd5",
    "passenger_drop_time": "2025-12-18T09:20:21.763Z",
    "passengers_arrived": 15,
    "passengers_departing": 35,
    "payment_amount": 150000,
    "payment_by": "mjbgk5pl-vdox8pc7xqn",
    "payment_method": "cash",
    "payment_shift_id": "mjbgk8rq-frkuzzav2ld",
    "payment_time": "2025-12-18T09:50:21.763Z",
    "permit_shift_id": "mjbgk8rq-frkuzzav2ld",
    "permit_status": "approved",
    "planned_departure_time": "2025-12-18T10:10:21.763Z",
    "route_id": "mjbgk88n-kzo1at10yzp",
    "schedule_id": "mjbgk979-qwjdq3k8lh8",
    "seat_count": 40,
    "transport_order_code": "LENH-001",
    "updated_at": "2025-12-23T08:24:44.219Z",
    "vehicle_id": "mjbgk631-jxo57s2rgw"
  },
  {
    "_firebase_id": "mjbgk9j7-5qmqhp955zv",
    "boarding_permit_by": "mjbgk5pl-cdj0zugj29a",
    "boarding_permit_by_name": "System Administrator",
    "boarding_permit_time": "2025-12-20T14:05:11+07:00",
    "created_at": "2025-12-18T13:00:21.763Z",
    "current_status": "cancelled",
    "departure_order_by": "mjbgk5pl-cdj0zugj29a",
    "departure_order_by_name": "System Administrator",
    "departure_order_shift_id": "mjbgk8rq-197glyortqd",
    "departure_order_time": "2025-12-20T23:24:58+07:00",
    "driver_full_name": "Trần Văn Xế",
    "driver_id": "mjbgk6zt-aa9b9rzbv0a",
    "entry_by": "mjbgk5pl-7lrvnqwbbd5",
    "entry_shift_id": "mjbgk8rq-v4u2c6zkn2k",
    "entry_time": "2025-12-18T13:00:21.763Z",
    "exit_by": "mjbgk5pl-cdj0zugj29a",
    "exit_by_name": "System Administrator",
    "exit_shift_id": "mjbgk8rq-197glyortqd",
    "exit_time": "2025-12-20T23:25:59.031Z",
    "id": "mjbgk9j7-5qmqhp955zv",
    "metadata": {
      "cancellation_reason": "Test",
      "cancelled_at": "2025-12-23T08:23:28.954Z",
      "cancelled_by": "mjbgk5pl-cdj0zugj29a",
      "cancelled_by_name": "System Administrator",
      "previous_status": "departed",
      "replacementVehicleId": "036b640c"
    },
    "passengers_departing": 8,
    "payment_amount": 5000000,
    "payment_by": "mjbgk5pl-cdj0zugj29a",
    "payment_by_name": "System Administrator",
    "payment_method": "cash",
    "payment_time": "2025-12-20T23:24:15+07:00",
    "permit_shift_id": "mjbgk8rq-905cj829qwr",
    "permit_status": "approved",
    "planned_departure_time": "2025-12-20T08:05:00.000Z",
    "route_id": "861",
    "seat_count": 1,
    "transport_order_code": "12121212",
    "updated_at": "2025-12-23T08:23:28.954Z",
    "vehicle_id": "mjbgk631-rj32kqs994"
  },
  {
    "_firebase_id": "mjbgk9j7-e12qxi0s8oc",
    "boarding_permit_by": "mjbgk5pl-7lrvnqwbbd5",
    "boarding_permit_time": "2025-12-18T12:40:21.763Z",
    "created_at": "2025-12-18T12:10:21.763Z",
    "current_status": "cancelled",
    "driver_full_name": "Lê Văn Lái",
    "driver_id": "mjbgk6zt-xf2b40jlyk",
    "entry_by": "mjbgk5pl-7lrvnqwbbd5",
    "entry_shift_id": "mjbgk8rq-v4u2c6zkn2k",
    "entry_time": "2025-12-18T12:10:21.763Z",
    "exit_by": "mjbgk5pl-cdj0zugj29a",
    "exit_by_name": "System Administrator",
    "exit_shift_id": "mjbgk8rq-905cj829qwr",
    "exit_time": "2025-12-20T08:13:24.881Z",
    "id": "mjbgk9j7-e12qxi0s8oc",
    "metadata": {
      "cancellation_reason": "test",
      "cancelled_at": "2025-12-23T08:24:11.015Z",
      "cancelled_by": "mjbgk5pl-cdj0zugj29a",
      "cancelled_by_name": "System Administrator",
      "previous_status": "departed"
    },
    "passenger_drop_by": "mjbgk5pl-7lrvnqwbbd5",
    "passenger_drop_time": "2025-12-18T12:20:21.763Z",
    "passengers_arrived": 10,
    "passengers_departing": 0,
    "payment_amount": 50000,
    "payment_by": "mjbgk5pl-cdj0zugj29a",
    "payment_by_name": "System Administrator",
    "payment_method": "cash",
    "payment_time": "2025-12-20T08:13:11+07:00",
    "permit_shift_id": "mjbgk8rq-v4u2c6zkn2k",
    "permit_status": "approved",
    "planned_departure_time": "2025-12-18T13:40:21.763Z",
    "route_id": "mjbgk88n-kzo1at10yzp",
    "schedule_id": "mjbgk979-bds03d6hoi6",
    "seat_count": 34,
    "transport_order_code": "LENH-002",
    "updated_at": "2025-12-23T08:24:11.016Z",
    "vehicle_id": "mjbgk631-uykjbaacz7l"
  },
  {
    "_firebase_id": "mjbjun1k-fwopb9akb3b",
    "boarding_permit_by": "mjbgk5pl-cdj0zugj29a",
    "boarding_permit_by_name": "System Administrator",
    "boarding_permit_time": "2025-12-20T08:14:54+07:00",
    "created_at": "2025-12-18T14:42:24.680Z",
    "current_status": "cancelled",
    "departure_order_by": "mjbgk5pl-cdj0zugj29a",
    "departure_order_by_name": "System Administrator",
    "departure_order_shift_id": "mjbgk8rq-905cj829qwr",
    "departure_order_time": "2025-12-22T16:01:05+07:00",
    "driver_full_name": "Nguyễn Văn Tài",
    "driver_id": "mjbgk6zs-fj0x22xt4yc",
    "entry_by": "",
    "entry_shift_id": "mjbgk8rq-v4u2c6zkn2k",
    "entry_time": "2025-12-18T14:42:01.305Z",
    "exit_by": "mjbgk5pl-cdj0zugj29a",
    "exit_by_name": "System Administrator",
    "exit_shift_id": "mjbgk8rq-905cj829qwr",
    "exit_time": "2025-12-22T16:01:17.338Z",
    "id": "mjbjun1k-fwopb9akb3b",
    "metadata": {
      "cancellation_reason": "test",
      "cancelled_at": "2025-12-23T08:24:18.499Z",
      "cancelled_by": "mjbgk5pl-cdj0zugj29a",
      "cancelled_by_name": "System Administrator",
      "previous_status": "departed"
    },
    "passengers_departing": 0,
    "payment_amount": 0,
    "payment_by": "mjbgk5pl-cdj0zugj29a",
    "payment_by_name": "System Administrator",
    "payment_method": "cash",
    "payment_time": "2025-12-20T23:27:04+07:00",
    "permit_shift_id": "mjbgk8rq-905cj829qwr",
    "permit_status": "approved",
    "planned_departure_time": "2025-12-20T07:01:00.000Z",
    "route_id": "mjbgk88n-ckbr0ii3wym",
    "route_name": "TP.HCM - Cần Thơ",
    "route_type": "Intercity",
    "seat_count": 1,
    "transport_order_code": "0",
    "updated_at": "2025-12-23T08:24:18.499Z",
    "vehicle_id": "mjbjpfid-fxe29zw5n2t"
  },
  {
    "_firebase_id": "mjd2n4hf-gn1t6z95rxm",
    "boarding_permit_by": "mjbgk5pl-cdj0zugj29a",
    "boarding_permit_by_name": "System Administrator",
    "boarding_permit_time": "2025-12-20T00:32:03+07:00",
    "created_at": "2025-12-19T16:16:12.915Z",
    "current_status": "cancelled",
    "departure_order_by": "mjbgk5pl-cdj0zugj29a",
    "departure_order_by_name": "System Administrator",
    "departure_order_shift_id": "mjbgk8rq-v4u2c6zkn2k",
    "departure_order_time": "2025-12-20T20:46:23+07:00",
    "driver_full_name": "Nguyễn Văn Tài",
    "driver_id": "mjbgk6zs-fj0x22xt4yc",
    "entry_by": "mjbgk5pl-cdj0zugj29a",
    "entry_by_name": "System Administrator",
    "entry_shift_id": "mjbgk8rq-197glyortqd",
    "entry_time": "2025-12-19T23:15:59.187Z",
    "exit_by": "mjbgk5pl-cdj0zugj29a",
    "exit_by_name": "System Administrator",
    "exit_shift_id": "mjbgk8rq-v4u2c6zkn2k",
    "exit_time": "2025-12-20T23:08:47.866Z",
    "id": "mjd2n4hf-gn1t6z95rxm",
    "metadata": {
      "cancellation_reason": "test",
      "cancelled_at": "2025-12-23T08:24:30.111Z",
      "cancelled_by": "mjbgk5pl-cdj0zugj29a",
      "cancelled_by_name": "System Administrator",
      "previous_status": "departed"
    },
    "passengers_departing": 8,
    "payment_amount": 5000000,
    "payment_by": "mjbgk5pl-cdj0zugj29a",
    "payment_by_name": "System Administrator",
    "payment_method": "cash",
    "payment_time": "2025-12-20T15:32:36+07:00",
    "permit_shift_id": "mjbgk8rq-197glyortqd",
    "permit_status": "approved",
    "planned_departure_time": "2025-12-19T21:31:00.000Z",
    "route_id": "mjbgk88n-kzo1at10yzp",
    "route_name": "TP.HCM - Đà Lạt",
    "route_type": "Intercity",
    "schedule_id": "mjbgk979-bds03d6hoi6",
    "seat_count": 16,
    "transport_order_code": "dffsdfdsfsdfsdfdsf",
    "updated_at": "2025-12-23T08:24:30.111Z",
    "vehicle_id": "mjcwg2fs-f7cd94ehknt",
    "vehicle_operator_code": "KUMHO",
    "vehicle_operator_id": "mjbgk5ww-609cwki15r",
    "vehicle_operator_name": "Công ty TNHH Vận tải Kumho Samco",
    "vehicle_plate_number": "98H07480"
  },
  {
    "_firebase_id": "mjdt2aph-h2o03aqju7c",
    "boarding_permit_by": "mjbgk5pl-cdj0zugj29a",
    "boarding_permit_by_name": "System Administrator",
    "boarding_permit_time": "2025-12-22T15:57:54+07:00",
    "created_at": "2025-12-20T04:35:50.837Z",
    "current_status": "cancelled",
    "departure_order_by": "mjbgk5pl-cdj0zugj29a",
    "departure_order_by_name": "System Administrator",
    "departure_order_shift_id": "mjbgk8rq-905cj829qwr",
    "departure_order_time": "2025-12-22T16:01:07+07:00",
    "driver_full_name": "",
    "entry_by": "mjbgk5pl-cdj0zugj29a",
    "entry_by_name": "System Administrator",
    "entry_shift_id": "mjbgk8rq-905cj829qwr",
    "entry_time": "2025-12-20T11:35:44.419Z",
    "exit_by": "mjbgk5pl-cdj0zugj29a",
    "exit_by_name": "System Administrator",
    "exit_shift_id": "mjbgk8rq-905cj829qwr",
    "exit_time": "2025-12-22T16:01:17.338Z",
    "id": "mjdt2aph-h2o03aqju7c",
    "metadata": {
      "cancellation_reason": "test",
      "cancelled_at": "2025-12-23T08:23:42.106Z",
      "cancelled_by": "mjbgk5pl-cdj0zugj29a",
      "cancelled_by_name": "System Administrator",
      "previous_status": "departed",
      "replacementVehicleId": "d8f95eb7"
    },
    "passengers_departing": 0,
    "payment_amount": 500000,
    "payment_by": "mjbgk5pl-cdj0zugj29a",
    "payment_by_name": "System Administrator",
    "payment_method": "cash",
    "payment_time": "2025-12-22T16:00:59+07:00",
    "permit_shift_id": "mjbgk8rq-905cj829qwr",
    "permit_status": "approved",
    "planned_departure_time": "2025-12-22T09:56:00.000Z",
    "route_id": "117",
    "seat_count": 50,
    "transport_order_code": "Lenh 304",
    "updated_at": "2025-12-23T08:23:42.106Z",
    "vehicle_id": "legacy_17",
    "vehicle_operator_name": "CÔNG TY TNHH XNK VÀ TM QUỐC TẾ QUANG PHÁT ",
    "vehicle_plate_number": "98RM02782"
  },
  {
    "_firebase_id": "mjid7oj1-0g0sxxqf3m",
    "boarding_permit_by": "mjbgk5pl-cdj0zugj29a",
    "boarding_permit_by_name": "System Administrator",
    "boarding_permit_time": "2025-12-25T17:01:55+07:00",
    "created_at": "2025-12-23T09:10:59.053Z",
    "current_status": "departed",
    "driver_full_name": "",
    "entry_by": "mjbgk5pl-cdj0zugj29a",
    "entry_by_name": "System Administrator",
    "entry_shift_id": "mjbgk8rq-905cj829qwr",
    "entry_time": "2025-12-23T16:10:56.217Z",
    "exit_by": "mjbgk5pl-cdj0zugj29a",
    "exit_by_name": "System Administrator",
    "exit_shift_id": "mjbgk8rq-905cj829qwr",
    "exit_time": "2025-12-25T17:02:22.147Z",
    "id": "mjid7oj1-0g0sxxqf3m",
    "passengers_departing": 15,
    "payment_amount": 0,
    "payment_by": "mjbgk5pl-cdj0zugj29a",
    "payment_by_name": "System Administrator",
    "payment_method": "cash",
    "payment_time": "2025-12-25T17:02:14+07:00",
    "permit_shift_id": "mjbgk8rq-905cj829qwr",
    "permit_status": "approved",
    "planned_departure_time": "2025-12-25T08:20:00.000Z",
    "route_id": "0124_1120_A",
    "seat_count": 15,
    "transport_order_code": "0",
    "updated_at": "2025-12-25T10:02:27.150Z",
    "vehicle_id": "legacy_45cc5d86",
    "vehicle_plate_number": "11A09075"
  },
  {
    "_firebase_id": "mjidnig7-b1e5dnmct2b",
    "boarding_permit_by": "mjbgk5pl-cdj0zugj29a",
    "boarding_permit_by_name": "System Administrator",
    "boarding_permit_time": "2025-12-29T22:36:27+07:00",
    "created_at": "2025-12-23T09:23:17.671Z",
    "current_status": "cancelled",
    "driver_full_name": "",
    "entry_by": "mjbgk5pl-cdj0zugj29a",
    "entry_by_name": "System Administrator",
    "entry_shift_id": "mjbgk8rq-905cj829qwr",
    "entry_time": "2025-12-23T17:26:00.000Z",
    "id": "mjidnig7-b1e5dnmct2b",
    "metadata": {
      "cancellation_reason": "sai thông tin",
      "cancelled_at": "2025-12-29T15:39:08.655Z",
      "cancelled_by": "mjbgk5pl-cdj0zugj29a",
      "cancelled_by_name": "System Administrator",
      "previous_status": "permit_issued",
      "replacementVehicleId": "legacy_c1b7cb8f"
    },
    "permit_shift_id": "mjbgk8rq-v4u2c6zkn2k",
    "permit_status": "approved",
    "planned_departure_time": "2025-12-26T17:25:00.000Z",
    "route_id": "0124_1120_A",
    "seat_count": 11,
    "transport_order_code": "6666666",
    "updated_at": "2025-12-29T15:39:08.655Z",
    "vehicle_id": "legacy_0ef691f9",
    "vehicle_plate_number": "98B01464"
  },
  {
    "_firebase_id": "mjido3gl-zl6vaz293eq",
    "boarding_permit_by": "mjbgk5pl-cdj0zugj29a",
    "boarding_permit_by_name": "System Administrator",
    "boarding_permit_time": "2025-12-29T22:50:57+07:00",
    "created_at": "2025-12-23T09:23:44.901Z",
    "current_status": "departed",
    "driver_full_name": "",
    "entry_by": "mjbgk5pl-cdj0zugj29a",
    "entry_by_name": "System Administrator",
    "entry_shift_id": "mjbgk8rq-905cj829qwr",
    "entry_time": "2025-12-23T16:23:39.561Z",
    "exit_by": "mjbgk5pl-cdj0zugj29a",
    "exit_by_name": "System Administrator",
    "exit_shift_id": "mjbgk8rq-v4u2c6zkn2k",
    "exit_time": "2025-12-29T22:53:52.485Z",
    "id": "mjido3gl-zl6vaz293eq",
    "metadata": {
      "replacementVehicleId": "legacy_c1b7cb8f"
    },
    "passengers_departing": 0,
    "payment_amount": 50000,
    "payment_by": "mjbgk5pl-cdj0zugj29a",
    "payment_by_name": "System Administrator",
    "payment_method": "cash",
    "payment_time": "2025-12-29T22:53:29+07:00",
    "permit_shift_id": "mjbgk8rq-v4u2c6zkn2k",
    "permit_status": "approved",
    "planned_departure_time": "2025-12-29T15:50:00.000Z",
    "route_id": "0124_1120_A",
    "seat_count": 12,
    "transport_order_code": "7777777",
    "updated_at": "2025-12-29T15:53:52.556Z",
    "vehicle_id": "legacy_37374244",
    "vehicle_operator_name": "CÔNG TY TNHIH TM DỊCH VỤ VẬN TẢI HỦNG CƯỜNG",
    "vehicle_plate_number": "99H07506"
  },
  {
    "_firebase_id": "mjio364l-z5x3451fq8",
    "boarding_permit_by": "mjbgk5pl-cdj0zugj29a",
    "boarding_permit_by_name": "System Administrator",
    "boarding_permit_time": "2025-12-29T22:59:34+07:00",
    "created_at": "2025-12-23T14:15:24.358Z",
    "current_status": "departed",
    "driver_full_name": "",
    "entry_by": "mjbgk5pl-cdj0zugj29a",
    "entry_by_name": "System Administrator",
    "entry_shift_id": "mjbgk8rq-v4u2c6zkn2k",
    "entry_time": "2025-12-23T21:13:52.295Z",
    "exit_by": "mjbgk5pl-cdj0zugj29a",
    "exit_by_name": "System Administrator",
    "exit_shift_id": "mjbgk8rq-v4u2c6zkn2k",
    "exit_time": "2025-12-29T23:00:03.056Z",
    "id": "mjio364l-z5x3451fq8",
    "passengers_departing": 0,
    "payment_amount": 20000,
    "payment_by": "mjbgk5pl-cdj0zugj29a",
    "payment_by_name": "System Administrator",
    "payment_method": "cash",
    "payment_time": "2025-12-29T22:59:42+07:00",
    "permit_shift_id": "mjbgk8rq-v4u2c6zkn2k",
    "permit_status": "approved",
    "planned_departure_time": "2025-12-29T15:59:00.000Z",
    "route_id": "0124_1120_A",
    "seat_count": 1,
    "transport_order_code": "99999",
    "updated_at": "2025-12-29T16:00:12.441Z",
    "vehicle_id": "legacy_014cdca5",
    "vehicle_plate_number": "11E00256"
  },
  {
    "_firebase_id": "mjio3agl-nylcb0i1v7k",
    "boarding_permit_by": "mjvoehos-xfb84bnjfw",
    "boarding_permit_by_name": "Lan Anh",
    "boarding_permit_time": "2026-01-02T00:09:13+07:00",
    "created_at": "2025-12-23T14:15:29.973Z",
    "current_status": "departed",
    "departure_order_by": "mjvoehos-xfb84bnjfw",
    "departure_order_by_name": "Lan Anh",
    "departure_order_shift_id": "mjbgk8rq-197glyortqd",
    "departure_order_time": "2026-01-02T00:10:46+07:00",
    "driver_full_name": "Nguyễn Văn Tài",
    "driver_id": "mjbgk6zs-fj0x22xt4yc",
    "entry_by": "mjbgk5pl-cdj0zugj29a",
    "entry_by_name": "System Administrator",
    "entry_image_url": "https://storage.googleapis.com/benxe-management-20251218.firebasestorage.app/dispatch-images/1767286905240-vrd659.jpg",
    "entry_shift_id": "mjbgk8rq-v4u2c6zkn2k",
    "entry_time": "2025-12-23T21:15:27.092Z",
    "exit_by": "mjvoehos-xfb84bnjfw",
    "exit_by_name": "Lan Anh",
    "exit_shift_id": "mjbgk8rq-197glyortqd",
    "exit_time": "2026-01-02T00:10:47.853Z",
    "id": "mjio3agl-nylcb0i1v7k",
    "passengers_departing": 8,
    "payment_amount": 0,
    "payment_by": "mjvoehos-xfb84bnjfw",
    "payment_by_name": "Lan Anh",
    "payment_method": "cash",
    "payment_time": "2026-01-02T00:10:38+07:00",
    "permit_shift_id": "mjbgk8rq-197glyortqd",
    "permit_status": "approved",
    "planned_departure_time": "2026-01-01T18:10:00.000Z",
    "route_id": "0124_1120_A",
    "seat_count": 22,
    "transport_order_code": "12456",
    "updated_at": "2026-01-01T17:10:49.362Z",
    "vehicle_id": "legacy_9a0c42ab",
    "vehicle_plate_number": "11F00233"
  },
  {
    "_firebase_id": "mjio3gf2-w6rwyxidw3",
    "created_at": "2025-12-23T14:15:37.694Z",
    "current_status": "cancelled",
    "driver_full_name": "",
    "entry_by": "mjbgk5pl-cdj0zugj29a",
    "entry_by_name": "System Administrator",
    "entry_shift_id": "mjbgk8rq-v4u2c6zkn2k",
    "entry_time": "2025-12-23T21:15:35.225Z",
    "id": "mjio3gf2-w6rwyxidw3",
    "metadata": {
      "cancellation_reason": "Hủy bởi người dùng từ màn hình điều độ",
      "cancelled_at": "2026-01-01T17:12:13.381Z",
      "cancelled_by": "mjvoehos-xfb84bnjfw",
      "cancelled_by_name": "Lan Anh",
      "previous_status": "entered"
    },
    "updated_at": "2026-01-01T17:12:13.381Z",
    "vehicle_id": "legacy_6410a66a",
    "vehicle_plate_number": "11F00050"
  },
  {
    "_firebase_id": "mjio3knc-pzviktqhi8g",
    "boarding_permit_by": "mjvoehos-xfb84bnjfw",
    "boarding_permit_by_name": "Lan Anh",
    "boarding_permit_time": "2026-01-02T00:12:21+07:00",
    "created_at": "2025-12-23T14:15:43.176Z",
    "current_status": "cancelled",
    "entry_by": "mjbgk5pl-cdj0zugj29a",
    "entry_by_name": "System Administrator",
    "entry_shift_id": "mjbgk8rq-v4u2c6zkn2k",
    "entry_time": "2025-12-23T21:15:38.927Z",
    "id": "mjio3knc-pzviktqhi8g",
    "metadata": {
      "cancellation_reason": "Hủy bởi người dùng từ màn hình điều độ",
      "cancelled_at": "2026-01-01T17:12:24.072Z",
      "cancelled_by": "mjvoehos-xfb84bnjfw",
      "cancelled_by_name": "Lan Anh",
      "previous_status": "permit_rejected"
    },
    "permit_shift_id": "mjbgk8rq-197glyortqd",
    "permit_status": "rejected",
    "planned_departure_time": "2026-01-01T17:12:20.722Z",
    "rejection_reason": "Giấy phép lái xe đã hết hạn hoặc sử dụng giấy phép lái xe giả",
    "updated_at": "2026-01-01T17:12:24.073Z",
    "vehicle_id": "legacy_65d838a1",
    "vehicle_operator_name": "NGUYỄN THỊ NGỌC",
    "vehicle_plate_number": "11H00191"
  },
  {
    "_firebase_id": "mjio3ny4-uwxyfv8xqu9",
    "boarding_permit_by": "mjvoehos-xfb84bnjfw",
    "boarding_permit_by_name": "Lan Anh",
    "boarding_permit_time": "2026-01-02T00:16:16+07:00",
    "created_at": "2025-12-23T14:15:47.452Z",
    "current_status": "cancelled",
    "driver_full_name": "Nguyễn Văn Tài",
    "driver_id": "mjbgk6zs-fj0x22xt4yc",
    "entry_by": "mjbgk5pl-cdj0zugj29a",
    "entry_by_name": "System Administrator",
    "entry_shift_id": "mjbgk8rq-v4u2c6zkn2k",
    "entry_time": "2025-12-23T21:15:44.891Z",
    "id": "mjio3ny4-uwxyfv8xqu9",
    "metadata": {
      "cancellation_reason": "khong có tiền",
      "cancelled_at": "2026-01-01T17:30:22.283Z",
      "cancelled_by": "mjvoehos-xfb84bnjfw",
      "cancelled_by_name": "Lan Anh",
      "previous_status": "permit_issued"
    },
    "permit_shift_id": "mjbgk8rq-197glyortqd",
    "permit_status": "approved",
    "planned_departure_time": "2026-01-01T18:16:00.000Z",
    "route_id": "0124_1221_B",
    "seat_count": 12,
    "transport_order_code": "98788",
    "updated_at": "2026-01-01T17:30:22.283Z",
    "vehicle_id": "legacy_e6fba7c9",
    "vehicle_plate_number": "11H00425"
  },
  {
    "_firebase_id": "mjio3r3r-3e138pqkxal",
    "boarding_permit_by": "mjvoehos-xfb84bnjfw",
    "boarding_permit_by_name": "Lan Anh",
    "boarding_permit_time": "2026-01-02T00:32:21+07:00",
    "created_at": "2025-12-23T14:15:51.543Z",
    "current_status": "departure_ordered",
    "departure_order_by": "mjvoehos-xfb84bnjfw",
    "departure_order_by_name": "Lan Anh",
    "departure_order_shift_id": "mjbgk8rq-v4u2c6zkn2k",
    "departure_order_time": "2026-01-03T18:03:21+07:00",
    "driver_full_name": "Trần Văn Xế",
    "driver_id": "mjbgk6zt-aa9b9rzbv0a",
    "entry_by": "mjbgk5pl-cdj0zugj29a",
    "entry_by_name": "System Administrator",
    "entry_shift_id": "mjbgk8rq-v4u2c6zkn2k",
    "entry_time": "2025-12-23T21:15:49.017Z",
    "id": "mjio3r3r-3e138pqkxal",
    "passengers_departing": 8,
    "payment_amount": 200000,
    "payment_by": "mjvoehos-xfb84bnjfw",
    "payment_by_name": "Lan Anh",
    "payment_method": "cash",
    "payment_time": "2026-01-03T18:03:13+07:00",
    "permit_shift_id": "mjbgk8rq-197glyortqd",
    "permit_status": "approved",
    "planned_departure_time": "2026-01-01T19:34:00.000Z",
    "route_id": "0124_1120_A",
    "seat_count": 12,
    "transport_order_code": "LENH001",
    "updated_at": "2026-01-03T11:03:21.839Z",
    "vehicle_id": "legacy_6433b093",
    "vehicle_plate_number": "11H00817"
  },
  {
    "_firebase_id": "mjio3v78-ar4rl3fox4",
    "boarding_permit_by": "mjvoehos-xfb84bnjfw",
    "boarding_permit_by_name": "Lan Anh",
    "boarding_permit_time": "2026-01-03T18:01:17+07:00",
    "created_at": "2025-12-23T14:15:56.852Z",
    "current_status": "departure_ordered",
    "departure_order_by": "mjvoehos-xfb84bnjfw",
    "departure_order_by_name": "Lan Anh",
    "departure_order_shift_id": "mjbgk8rq-v4u2c6zkn2k",
    "departure_order_time": "2026-01-03T18:03:33+07:00",
    "entry_by": "mjbgk5pl-cdj0zugj29a",
    "entry_by_name": "System Administrator",
    "entry_image_url": "",
    "entry_shift_id": "mjbgk8rq-v4u2c6zkn2k",
    "entry_time": "2025-12-23T21:15:54.363Z",
    "id": "mjio3v78-ar4rl3fox4",
    "passengers_departing": 8,
    "payment_amount": 0,
    "payment_by": "mjvoehos-xfb84bnjfw",
    "payment_by_name": "Lan Anh",
    "payment_method": "cash",
    "payment_time": "2026-01-03T18:03:27+07:00",
    "permit_shift_id": "mjbgk8rq-v4u2c6zkn2k",
    "permit_status": "approved",
    "planned_departure_time": "2026-01-03T11:03:00.000Z",
    "route_id": "0124_1120_A",
    "seat_count": 4,
    "transport_order_code": "LENH004",
    "updated_at": "2026-01-03T11:03:33.635Z",
    "vehicle_id": "legacy_4b8482f6",
    "vehicle_plate_number": "11H00803"
  },
  {
    "_firebase_id": "mjl9vmrw-4paqtg8hyf",
    "boarding_permit_by": "mjvoehos-xfb84bnjfw",
    "boarding_permit_by_name": "Lan Anh",
    "boarding_permit_time": "2026-01-03T18:12:58+07:00",
    "created_at": "2025-12-25T10:00:56.588Z",
    "current_status": "permit_issued",
    "entry_by": "mjbgk5pl-cdj0zugj29a",
    "entry_by_name": "System Administrator",
    "entry_shift_id": "mjbgk8rq-905cj829qwr",
    "entry_time": "2025-12-25T17:00:50.016Z",
    "id": "mjl9vmrw-4paqtg8hyf",
    "permit_shift_id": "mjbgk8rq-v4u2c6zkn2k",
    "permit_status": "approved",
    "planned_departure_time": "2026-01-03T11:14:00.000Z",
    "route_id": "0124_1213_A",
    "seat_count": 23,
    "transport_order_code": "LENH009",
    "updated_at": "2026-01-03T11:12:58.706Z",
    "vehicle_id": "legacy_c09fe0d5",
    "vehicle_plate_number": "12H03019"
  },
  {
    "_firebase_id": "mjlon39i-4vy4diz4mh5",
    "created_at": "2025-12-25T16:54:12.294Z",
    "current_status": "cancelled",
    "driver_full_name": "",
    "entry_by": "mjbgk5pl-cdj0zugj29a",
    "entry_by_name": "System Administrator",
    "entry_shift_id": "mjbgk8rq-197glyortqd",
    "entry_time": "2025-12-25T23:54:09.498Z",
    "id": "mjlon39i-4vy4diz4mh5",
    "metadata": {
      "cancellation_reason": "Hủy bởi người dùng từ màn hình điều độ",
      "cancelled_at": "2026-01-03T14:36:15.095Z",
      "cancelled_by": "mjvoehos-xfb84bnjfw",
      "cancelled_by_name": "Lan Anh",
      "previous_status": "entered"
    },
    "updated_at": "2026-01-03T14:36:15.095Z",
    "vehicle_id": "legacy_45cc5d86",
    "vehicle_plate_number": "11A09075"
  },
  {
    "_firebase_id": "mjlv6lhj-vl0bs6aw1e9",
    "created_at": "2025-12-25T19:57:20.071Z",
    "current_status": "entered",
    "driver_full_name": "",
    "entry_by": "mjbgk5pl-cdj0zugj29a",
    "entry_by_name": "System Administrator",
    "entry_shift_id": "mjbgk8rq-197glyortqd",
    "entry_time": "2025-12-26T02:57:15.598Z",
    "id": "mjlv6lhj-vl0bs6aw1e9",
    "updated_at": "2025-12-25T19:57:20.071Z",
    "vehicle_id": "legacy_6e4fd0cb",
    "vehicle_plate_number": "98H08152"
  },
  {
    "_firebase_id": "mjqrqp6v-gezeclqz8c",
    "created_at": "2025-12-29T06:19:50.407Z",
    "current_status": "cancelled",
    "driver_full_name": "",
    "entry_by": "mjbgk5pl-cdj0zugj29a",
    "entry_by_name": "System Administrator",
    "entry_shift_id": "mjbgk8rq-905cj829qwr",
    "entry_time": "2025-12-29T13:19:46.507Z",
    "id": "mjqrqp6v-gezeclqz8c",
    "metadata": {
      "cancellation_reason": "Hủy bởi người dùng từ màn hình điều độ",
      "cancelled_at": "2026-01-03T14:36:12.689Z",
      "cancelled_by": "mjvoehos-xfb84bnjfw",
      "cancelled_by_name": "Lan Anh",
      "previous_status": "entered"
    },
    "updated_at": "2026-01-03T14:36:12.689Z",
    "vehicle_id": "legacy_878eafc2",
    "vehicle_plate_number": "11H00854"
  },
  {
    "_firebase_id": "mjqrqvu2-h7gniairbh8",
    "created_at": "2025-12-29T06:19:59.018Z",
    "current_status": "entered",
    "driver_full_name": "",
    "entry_by": "mjbgk5pl-cdj0zugj29a",
    "entry_by_name": "System Administrator",
    "entry_shift_id": "mjbgk8rq-905cj829qwr",
    "entry_time": "2025-12-29T13:19:55.925Z",
    "id": "mjqrqvu2-h7gniairbh8",
    "updated_at": "2025-12-29T06:19:59.018Z",
    "vehicle_id": "legacy_bbc77652",
    "vehicle_plate_number": "11H00894"
  },
  {
    "_firebase_id": "mjqrr0y3-63rth6oyu1l",
    "created_at": "2025-12-29T06:20:05.643Z",
    "current_status": "entered",
    "driver_full_name": "",
    "entry_by": "mjbgk5pl-cdj0zugj29a",
    "entry_by_name": "System Administrator",
    "entry_shift_id": "mjbgk8rq-905cj829qwr",
    "entry_time": "2025-12-29T13:20:02.456Z",
    "id": "mjqrr0y3-63rth6oyu1l",
    "updated_at": "2025-12-29T06:20:05.643Z",
    "vehicle_id": "legacy_76bd686d",
    "vehicle_plate_number": "14G00550"
  },
  {
    "_firebase_id": "mjqrr60j-tcspup72ijm",
    "created_at": "2025-12-29T06:20:12.211Z",
    "current_status": "cancelled",
    "driver_full_name": "",
    "entry_by": "mjbgk5pl-cdj0zugj29a",
    "entry_by_name": "System Administrator",
    "entry_shift_id": "mjbgk8rq-905cj829qwr",
    "entry_time": "2025-12-23T15:49:00.000Z",
    "id": "mjqrr60j-tcspup72ijm",
    "metadata": {
      "cancellation_reason": "Hủy bởi người dùng từ màn hình điều độ",
      "cancelled_at": "2026-01-03T14:36:09.863Z",
      "cancelled_by": "mjvoehos-xfb84bnjfw",
      "cancelled_by_name": "Lan Anh",
      "previous_status": "entered"
    },
    "updated_at": "2026-01-03T14:36:09.863Z",
    "vehicle_id": "legacy_434c64c3",
    "vehicle_plate_number": "22F00152"
  },
  {
    "_firebase_id": "mjqww6oc-nn6dx08ysq",
    "created_at": "2025-12-29T08:44:04.428Z",
    "current_status": "departed",
    "driver_full_name": "",
    "entry_by": "mjbgk5pl-cdj0zugj29a",
    "entry_by_name": "System Administrator",
    "entry_shift_id": "mjbgk8rq-905cj829qwr",
    "entry_time": "2025-12-29T15:49:58.000Z",
    "exit_by": "mjvoehos-xfb84bnjfw",
    "exit_by_name": "Lan Anh",
    "exit_time": "2026-01-03T18:03:06+07:00",
    "id": "mjqww6oc-nn6dx08ysq",
    "payment_amount": 0,
    "payment_by": "mjbgk5pl-cdj0zugj29a",
    "payment_by_name": "System Administrator",
    "payment_method": "cash",
    "payment_time": "2026-01-02T20:56:21+07:00",
    "updated_at": "2026-01-03T11:03:06.306Z",
    "vehicle_id": "legacy_fdc458cb",
    "vehicle_plate_number": "98B01460"
  },
  {
    "_firebase_id": "mjra6z12-ydtq0y1rwus",
    "created_at": "2025-12-29T14:56:22.742Z",
    "current_status": "cancelled",
    "driver_full_name": "",
    "entry_by": "mjbgk5pl-cdj0zugj29a",
    "entry_by_name": "System Administrator",
    "entry_shift_id": "mjbgk8rq-v4u2c6zkn2k",
    "entry_time": "2025-12-29T21:56:17.251Z",
    "id": "mjra6z12-ydtq0y1rwus",
    "metadata": {
      "cancellation_reason": "Hủy bởi người dùng từ màn hình điều độ",
      "cancelled_at": "2026-01-03T11:26:24.433Z",
      "cancelled_by": "mjvoehos-xfb84bnjfw",
      "cancelled_by_name": "Lan Anh",
      "previous_status": "entered"
    },
    "updated_at": "2026-01-03T11:26:24.433Z",
    "vehicle_id": "legacy_fb41de5e",
    "vehicle_plate_number": "14H05096"
  },
  {
    "_firebase_id": "mjrct1pz-ypadps6qaz",
    "created_at": "2025-12-29T16:09:31.895Z",
    "current_status": "cancelled",
    "driver_full_name": "",
    "entry_by": "mjbgk5pl-cdj0zugj29a",
    "entry_by_name": "System Administrator",
    "entry_shift_id": "mjbgk8rq-v4u2c6zkn2k",
    "entry_time": "2025-12-29T23:08:05.753Z",
    "id": "mjrct1pz-ypadps6qaz",
    "metadata": {
      "cancellation_reason": "Hủy bởi người dùng từ màn hình điều độ",
      "cancelled_at": "2026-01-03T11:26:12.620Z",
      "cancelled_by": "mjvoehos-xfb84bnjfw",
      "cancelled_by_name": "Lan Anh",
      "previous_status": "passengers_dropped"
    },
    "passenger_drop_by": "mjbgk5pl-cdj0zugj29a",
    "passenger_drop_by_name": "System Administrator",
    "passenger_drop_time": "2025-12-29T23:09:32+07:00",
    "passengers_arrived": 2,
    "route_id": "mjbgk88n-vrk61vz71d",
    "route_name": "TP.HCM - Vũng Tàu",
    "route_type": "Intercity",
    "updated_at": "2026-01-03T11:26:12.620Z",
    "vehicle_id": "legacy_5615e47f",
    "vehicle_plate_number": "19H04677"
  },
  {
    "_firebase_id": "mjwwp127-dsr5qerz9gf",
    "created_at": "2026-01-02T13:25:07.615Z",
    "current_status": "cancelled",
    "driver_full_name": "",
    "entry_by": "mjbgk5pl-cdj0zugj29a",
    "entry_by_name": "System Administrator",
    "entry_shift_id": "mjbgk8rq-frkuzzav2ld",
    "entry_time": "2026-01-07T20:23:00.000Z",
    "id": "mjwwp127-dsr5qerz9gf",
    "metadata": {
      "cancellation_reason": "Hủy bởi người dùng từ màn hình điều độ",
      "cancelled_at": "2026-01-03T11:26:22.235Z",
      "cancelled_by": "mjvoehos-xfb84bnjfw",
      "cancelled_by_name": "Lan Anh",
      "previous_status": "passengers_dropped"
    },
    "passenger_drop_by": "mjbgk5pl-cdj0zugj29a",
    "passenger_drop_by_name": "System Administrator",
    "passenger_drop_time": "2026-01-02T20:25:07+07:00",
    "passengers_arrived": 15,
    "route_id": "mjbgk88n-ckbr0ii3wym",
    "route_name": "TP.HCM - Cần Thơ",
    "route_type": "Intercity",
    "updated_at": "2026-01-03T11:26:22.235Z",
    "vehicle_id": "legacy_9a0c42ab",
    "vehicle_plate_number": "11F00233"
  },
  {
    "_firebase_id": "mjwws32i-y00xchrqqkd",
    "boarding_permit_by": "mjbgk5pl-cdj0zugj29a",
    "boarding_permit_by_name": "System Administrator",
    "boarding_permit_time": "2026-01-02T20:36:59+07:00",
    "created_at": "2026-01-02T13:27:30.186Z",
    "current_status": "paid",
    "driver_full_name": "Lê Văn Lái",
    "driver_id": "mjbgk6zt-xf2b40jlyk",
    "entry_by": "mjbgk5pl-cdj0zugj29a",
    "entry_by_name": "System Administrator",
    "entry_shift_id": "mjbgk8rq-frkuzzav2ld",
    "entry_time": "2026-01-03T20:26:00.000Z",
    "id": "mjwws32i-y00xchrqqkd",
    "passenger_drop_by": "mjbgk5pl-cdj0zugj29a",
    "passenger_drop_by_name": "System Administrator",
    "passenger_drop_time": "2026-01-02T20:27:30+07:00",
    "passengers_arrived": 12,
    "payment_amount": 100000,
    "payment_by": "mjvoehos-xfb84bnjfw",
    "payment_by_name": "Lan Anh",
    "payment_method": "cash",
    "payment_time": "2026-01-03T22:58:33+07:00",
    "permit_shift_id": "mjbgk8rq-frkuzzav2ld",
    "permit_status": "approved",
    "planned_departure_time": "2026-01-02T13:37:00.000Z",
    "route_id": "mjbgk88n-ckbr0ii3wym",
    "route_name": "TP.HCM - Cần Thơ",
    "route_type": "Intercity",
    "seat_count": 11,
    "transport_order_code": "LENH555",
    "updated_at": "2026-01-03T15:58:33.313Z",
    "vehicle_id": "legacy_c1b7cb8f",
    "vehicle_plate_number": "11B00408"
  },
  {
    "_firebase_id": "mjwx5xik-tcofpglpk8h",
    "boarding_permit_by": "mjbgk5pl-cdj0zugj29a",
    "boarding_permit_by_name": "System Administrator",
    "boarding_permit_time": "2026-01-02T20:43:21+07:00",
    "created_at": "2026-01-02T13:38:16.172Z",
    "current_status": "departed",
    "driver_full_name": "Nguyễn Văn Tài",
    "driver_id": "mjbgk6zs-fj0x22xt4yc",
    "entry_by": "mjbgk5pl-cdj0zugj29a",
    "entry_by_name": "System Administrator",
    "entry_image_url": "https://storage.googleapis.com/benxe-management-20251218.firebasestorage.app/dispatch-images/1767361241508-y4tor.jpg",
    "entry_shift_id": "mjbgk8rq-frkuzzav2ld",
    "entry_time": "2026-01-02T20:37:39.586Z",
    "exit_by": "mjbgk5pl-cdj0zugj29a",
    "exit_by_name": "System Administrator",
    "exit_shift_id": "mjbgk8rq-frkuzzav2ld",
    "exit_time": "2026-01-02T20:47:00.466Z",
    "id": "mjwx5xik-tcofpglpk8h",
    "passenger_drop_by": "mjbgk5pl-cdj0zugj29a",
    "passenger_drop_by_name": "System Administrator",
    "passenger_drop_time": "2026-01-02T20:38:16+07:00",
    "passengers_arrived": 20,
    "passengers_departing": 0,
    "payment_amount": 150000,
    "payment_by": "mjbgk5pl-cdj0zugj29a",
    "payment_by_name": "System Administrator",
    "payment_method": "cash",
    "payment_time": "2026-01-02T20:45:34+07:00",
    "permit_shift_id": "mjbgk8rq-frkuzzav2ld",
    "permit_status": "approved",
    "planned_departure_time": "2026-01-02T13:43:25.045Z",
    "route_id": "mjbgk88n-kzo1at10yzp",
    "route_name": "TP.HCM - Đà Lạt",
    "route_type": "Intercity",
    "schedule_id": "mjbgk979-bds03d6hoi6",
    "seat_count": 1,
    "transport_order_code": "3485485",
    "updated_at": "2026-01-02T13:47:02.072Z",
    "vehicle_id": "legacy_6410a66a",
    "vehicle_plate_number": "11F00050"
  },
  {
    "_firebase_id": "mjy7uzt4-zw7ol0fzo4p",
    "created_at": "2026-01-03T11:25:27.880Z",
    "current_status": "cancelled",
    "driver_full_name": "",
    "entry_by": "mjvoehos-xfb84bnjfw",
    "entry_by_name": "Lan Anh",
    "entry_shift_id": "mjbgk8rq-v4u2c6zkn2k",
    "entry_time": "2026-01-03T18:24:40.352Z",
    "id": "mjy7uzt4-zw7ol0fzo4p",
    "metadata": {
      "cancellation_reason": "Hủy bởi người dùng từ màn hình điều độ",
      "cancelled_at": "2026-01-03T11:26:09.779Z",
      "cancelled_by": "mjvoehos-xfb84bnjfw",
      "cancelled_by_name": "Lan Anh",
      "previous_status": "passengers_dropped"
    },
    "passenger_drop_by": "mjvoehos-xfb84bnjfw",
    "passenger_drop_by_name": "Lan Anh",
    "passenger_drop_time": "2026-01-03T18:25:28+07:00",
    "passengers_arrived": 12,
    "route_id": "mjbgk88n-ckbr0ii3wym",
    "route_name": "TP.HCM - Cần Thơ",
    "route_type": "Intercity",
    "updated_at": "2026-01-03T11:26:09.779Z",
    "vehicle_id": "legacy_6410a66a",
    "vehicle_plate_number": "11F00050"
  },
  {
    "_firebase_id": "mjy7wmc5-ikyc8v7u7fg",
    "created_at": "2026-01-03T11:26:43.733Z",
    "current_status": "passengers_dropped",
    "driver_full_name": "",
    "entry_by": "mjvoehos-xfb84bnjfw",
    "entry_by_name": "Lan Anh",
    "entry_shift_id": "mjbgk8rq-v4u2c6zkn2k",
    "entry_time": "2026-01-03T18:26:26.128Z",
    "id": "mjy7wmc5-ikyc8v7u7fg",
    "passenger_drop_by": "mjvoehos-xfb84bnjfw",
    "passenger_drop_by_name": "Lan Anh",
    "passenger_drop_time": "2026-01-03T18:26:43+07:00",
    "passengers_arrived": 11,
    "route_id": "mjbgk88n-ckbr0ii3wym",
    "route_name": "TP.HCM - Cần Thơ",
    "route_type": "Intercity",
    "updated_at": "2026-01-03T11:26:43.956Z",
    "vehicle_id": "legacy_9a0c42ab",
    "vehicle_plate_number": "11F00233"
  },
  {
    "_firebase_id": "mjy85vjq-yg4jf9euxg",
    "created_at": "2026-01-03T11:33:55.574Z",
    "current_status": "cancelled",
    "driver_full_name": "",
    "entry_by": "mjvoehos-xfb84bnjfw",
    "entry_by_name": "Lan Anh",
    "entry_shift_id": "mjbgk8rq-v4u2c6zkn2k",
    "entry_time": "2026-01-03T18:33:38.907Z",
    "id": "mjy85vjq-yg4jf9euxg",
    "metadata": {
      "cancellation_reason": "Hủy bởi người dùng từ màn hình điều độ",
      "cancelled_at": "2026-01-03T14:36:07.172Z",
      "cancelled_by": "mjvoehos-xfb84bnjfw",
      "cancelled_by_name": "Lan Anh",
      "previous_status": "passengers_dropped"
    },
    "passenger_drop_by": "mjvoehos-xfb84bnjfw",
    "passenger_drop_by_name": "Lan Anh",
    "passenger_drop_time": "2026-01-03T18:33:55+07:00",
    "passengers_arrived": 10,
    "route_id": "mjbgk88n-ckbr0ii3wym",
    "route_name": "TP.HCM - Cần Thơ",
    "route_type": "Intercity",
    "updated_at": "2026-01-03T14:36:07.172Z",
    "vehicle_id": "legacy_014cdca5",
    "vehicle_plate_number": "11E00256"
  },
  {
    "_firebase_id": "mjy9x120-ohz0smak6qo",
    "created_at": "2026-01-03T12:23:02.040Z",
    "current_status": "cancelled",
    "driver_full_name": "",
    "entry_by": "mjvoehos-xfb84bnjfw",
    "entry_by_name": "Lan Anh",
    "entry_shift_id": "mjbgk8rq-v4u2c6zkn2k",
    "entry_time": "2026-01-03T19:22:09.357Z",
    "id": "mjy9x120-ohz0smak6qo",
    "metadata": {
      "cancellation_reason": "Hủy bởi người dùng từ màn hình điều độ",
      "cancelled_at": "2026-01-03T14:36:05.113Z",
      "cancelled_by": "mjvoehos-xfb84bnjfw",
      "cancelled_by_name": "Lan Anh",
      "previous_status": "passengers_dropped"
    },
    "passenger_drop_by": "mjvoehos-xfb84bnjfw",
    "passenger_drop_by_name": "Lan Anh",
    "passenger_drop_time": "2026-01-03T19:23:02+07:00",
    "passengers_arrived": 12,
    "route_id": "0124_1123_A",
    "updated_at": "2026-01-03T14:36:05.113Z",
    "vehicle_id": "legacy_6410a66a",
    "vehicle_plate_number": "11F00050"
  },
  {
    "_firebase_id": "mjyampn9-t8a5sgl6kr",
    "created_at": "2026-01-03T12:43:00.309Z",
    "current_status": "cancelled",
    "driver_full_name": "",
    "entry_by": "mjvoehos-xfb84bnjfw",
    "entry_by_name": "Lan Anh",
    "entry_shift_id": "mjbgk8rq-v4u2c6zkn2k",
    "entry_time": "2026-01-03T19:42:45.091Z",
    "id": "mjyampn9-t8a5sgl6kr",
    "metadata": {
      "cancellation_reason": "Hủy bởi người dùng từ màn hình điều độ",
      "cancelled_at": "2026-01-03T14:36:02.766Z",
      "cancelled_by": "mjvoehos-xfb84bnjfw",
      "cancelled_by_name": "Lan Anh",
      "previous_status": "passengers_dropped"
    },
    "passenger_drop_by": "mjvoehos-xfb84bnjfw",
    "passenger_drop_by_name": "Lan Anh",
    "passenger_drop_time": "2026-01-03T19:43:00+07:00",
    "passengers_arrived": 12,
    "route_id": "0124_1213_A",
    "route_name": " - ",
    "route_type": "fixed",
    "updated_at": "2026-01-03T14:36:02.766Z",
    "vehicle_id": "legacy_6433b093",
    "vehicle_plate_number": "11H00817"
  },
  {
    "_firebase_id": "mjyaso0m-vn0f32mr3x",
    "created_at": "2026-01-03T12:47:38.134Z",
    "current_status": "cancelled",
    "driver_full_name": "",
    "entry_by": "mjvoehos-xfb84bnjfw",
    "entry_by_name": "Lan Anh",
    "entry_shift_id": "mjbgk8rq-v4u2c6zkn2k",
    "entry_time": "2026-01-03T19:47:27.146Z",
    "id": "mjyaso0m-vn0f32mr3x",
    "metadata": {
      "cancellation_reason": "Hủy bởi người dùng từ màn hình điều độ",
      "cancelled_at": "2026-01-03T14:36:00.219Z",
      "cancelled_by": "mjvoehos-xfb84bnjfw",
      "cancelled_by_name": "Lan Anh",
      "previous_status": "passengers_dropped"
    },
    "passenger_drop_by": "mjvoehos-xfb84bnjfw",
    "passenger_drop_by_name": "Lan Anh",
    "passenger_drop_time": "2026-01-03T19:47:38+07:00",
    "passengers_arrived": 12,
    "route_id": "0124_1120_A",
    "route_name": " - ",
    "route_type": "fixed",
    "updated_at": "2026-01-03T14:36:00.219Z",
    "vehicle_id": "legacy_fb41de5e",
    "vehicle_plate_number": "14H05096"
  },
  {
    "_firebase_id": "mjybkm6v-ahvu51el3s",
    "created_at": "2026-01-03T13:09:22.135Z",
    "current_status": "passengers_dropped",
    "driver_full_name": "",
    "entry_by": "mjvoehos-xfb84bnjfw",
    "entry_by_name": "Lan Anh",
    "entry_shift_id": "mjbgk8rq-v4u2c6zkn2k",
    "entry_time": "2026-01-03T20:09:11.340Z",
    "id": "mjybkm6v-ahvu51el3s",
    "passenger_drop_by": "mjvoehos-xfb84bnjfw",
    "passenger_drop_by_name": "Lan Anh",
    "passenger_drop_time": "2026-01-03T20:09:22+07:00",
    "passengers_arrived": 12,
    "route_id": "0124_1123_A",
    "route_name": " - ",
    "route_type": "fixed",
    "updated_at": "2026-01-03T13:09:22.549Z",
    "vehicle_id": "legacy_5615e47f",
    "vehicle_plate_number": "19H04677"
  },
  {
    "_firebase_id": "mjyblor8-xhsizcblceo",
    "created_at": "2026-01-03T13:10:12.116Z",
    "current_status": "cancelled",
    "driver_full_name": "",
    "entry_by": "mjvoehos-xfb84bnjfw",
    "entry_by_name": "Lan Anh",
    "entry_shift_id": "mjbgk8rq-v4u2c6zkn2k",
    "entry_time": "2026-01-03T20:10:00.585Z",
    "id": "mjyblor8-xhsizcblceo",
    "metadata": {
      "cancellation_reason": "Hủy bởi người dùng từ màn hình điều độ",
      "cancelled_at": "2026-01-03T14:35:56.480Z",
      "cancelled_by": "mjvoehos-xfb84bnjfw",
      "cancelled_by_name": "Lan Anh",
      "previous_status": "passengers_dropped"
    },
    "passenger_drop_by": "mjvoehos-xfb84bnjfw",
    "passenger_drop_by_name": "Lan Anh",
    "passenger_drop_time": "2026-01-03T20:10:12+07:00",
    "passengers_arrived": 12,
    "route_id": "0124_1123_A",
    "route_name": " - ",
    "route_type": "fixed",
    "updated_at": "2026-01-03T14:35:56.480Z",
    "vehicle_id": "legacy_46349715",
    "vehicle_plate_number": "19H10347"
  },
  {
    "_firebase_id": "mjybwkgz-s9o2ps3xqo8",
    "created_at": "2026-01-03T13:18:39.779Z",
    "current_status": "passengers_dropped",
    "driver_full_name": "",
    "entry_by": "mjvoehos-xfb84bnjfw",
    "entry_by_name": "Lan Anh",
    "entry_shift_id": "mjbgk8rq-v4u2c6zkn2k",
    "entry_time": "2026-01-03T20:18:28.923Z",
    "id": "mjybwkgz-s9o2ps3xqo8",
    "passenger_drop_by": "mjvoehos-xfb84bnjfw",
    "passenger_drop_by_name": "Lan Anh",
    "passenger_drop_time": "2026-01-03T20:18:40+07:00",
    "passengers_arrived": 123,
    "route_id": "0124_1123_A",
    "route_name": " - ",
    "route_type": "fixed",
    "updated_at": "2026-01-03T13:18:40.166Z",
    "vehicle_id": "legacy_3b151340",
    "vehicle_plate_number": "20F00285"
  },
  {
    "_firebase_id": "mjyelcjx-trb3yh7llr",
    "created_at": "2026-01-03T14:33:55.149Z",
    "current_status": "cancelled",
    "driver_full_name": "",
    "entry_by": "mjvoehos-xfb84bnjfw",
    "entry_by_name": "Lan Anh",
    "entry_shift_id": "mjbgk8rq-v4u2c6zkn2k",
    "entry_time": "2026-01-03T21:32:33.244Z",
    "id": "mjyelcjx-trb3yh7llr",
    "metadata": {
      "cancellation_reason": "Hủy bởi người dùng từ màn hình điều độ",
      "cancelled_at": "2026-01-03T14:35:51.264Z",
      "cancelled_by": "mjvoehos-xfb84bnjfw",
      "cancelled_by_name": "Lan Anh",
      "previous_status": "passengers_dropped"
    },
    "passenger_drop_by": "mjvoehos-xfb84bnjfw",
    "passenger_drop_by_name": "Lan Anh",
    "passenger_drop_time": "2026-01-03T21:33:55+07:00",
    "passengers_arrived": 13,
    "route_id": "0124_1120_A",
    "route_name": " - ",
    "route_type": "fixed",
    "updated_at": "2026-01-03T14:35:51.265Z",
    "vehicle_id": "legacy_4b8482f6",
    "vehicle_plate_number": "11H00803"
  },
  {
    "_firebase_id": "mjyeor65-l6l5xl11yg8",
    "created_at": "2026-01-03T14:36:34.061Z",
    "current_status": "passengers_dropped",
    "driver_full_name": "",
    "entry_by": "mjvoehos-xfb84bnjfw",
    "entry_by_name": "Lan Anh",
    "entry_shift_id": "mjbgk8rq-v4u2c6zkn2k",
    "entry_time": "2026-01-03T21:36:20.733Z",
    "id": "mjyeor65-l6l5xl11yg8",
    "passenger_drop_by": "mjvoehos-xfb84bnjfw",
    "passenger_drop_by_name": "Lan Anh",
    "passenger_drop_time": "2026-01-03T21:36:34+07:00",
    "passengers_arrived": 12,
    "route_id": "0124_1213_A",
    "route_name": " - ",
    "route_type": "fixed",
    "updated_at": "2026-01-03T14:36:34.509Z",
    "vehicle_id": "legacy_6410a66a",
    "vehicle_plate_number": "11F00050"
  },
  {
    "_firebase_id": "mjyepui0-rsnmgnuxvdb",
    "created_at": "2026-01-03T14:37:25.033Z",
    "current_status": "cancelled",
    "driver_full_name": "",
    "entry_by": "mjvoehos-xfb84bnjfw",
    "entry_by_name": "Lan Anh",
    "entry_shift_id": "mjbgk8rq-v4u2c6zkn2k",
    "entry_time": "2026-01-03T21:37:21.489Z",
    "id": "mjyepui0-rsnmgnuxvdb",
    "metadata": {
      "cancellation_reason": "Hủy bởi người dùng từ màn hình điều độ",
      "cancelled_at": "2026-01-03T14:37:36.094Z",
      "cancelled_by": "mjvoehos-xfb84bnjfw",
      "cancelled_by_name": "Lan Anh",
      "previous_status": "entered"
    },
    "updated_at": "2026-01-03T14:37:36.095Z",
    "vehicle_id": "legacy_4b8482f6",
    "vehicle_plate_number": "11H00803"
  },
  {
    "_firebase_id": "mjyeqfy6-azdkr8nw64d",
    "created_at": "2026-01-03T14:37:52.830Z",
    "current_status": "passengers_dropped",
    "driver_full_name": "",
    "entry_by": "mjvoehos-xfb84bnjfw",
    "entry_by_name": "Lan Anh",
    "entry_shift_id": "mjbgk8rq-v4u2c6zkn2k",
    "entry_time": "2026-01-03T21:37:38.008Z",
    "id": "mjyeqfy6-azdkr8nw64d",
    "passenger_drop_by": "mjvoehos-xfb84bnjfw",
    "passenger_drop_by_name": "Lan Anh",
    "passenger_drop_time": "2026-01-03T21:37:53+07:00",
    "passengers_arrived": 12,
    "route_id": "0124_1616_A",
    "route_name": " - ",
    "route_type": "fixed",
    "updated_at": "2026-01-03T14:37:53.184Z",
    "vehicle_id": "legacy_4b8482f6",
    "vehicle_plate_number": "11H00803"
  },
  {
    "_firebase_id": "mjyf763i-5oalyyn1niv",
    "created_at": "2026-01-03T14:50:53.214Z",
    "current_status": "passengers_dropped",
    "driver_full_name": "",
    "entry_by": "mjvoehos-xfb84bnjfw",
    "entry_by_name": "Lan Anh",
    "entry_shift_id": "mjbgk8rq-v4u2c6zkn2k",
    "entry_time": "2026-01-03T21:50:32.593Z",
    "id": "mjyf763i-5oalyyn1niv",
    "passenger_drop_by": "mjvoehos-xfb84bnjfw",
    "passenger_drop_by_name": "Lan Anh",
    "passenger_drop_time": "2026-01-03T21:50:53+07:00",
    "passengers_arrived": 12,
    "route_id": "0124_1123_A",
    "route_name": " - ",
    "route_type": "fixed",
    "updated_at": "2026-01-03T14:50:53.628Z",
    "vehicle_id": "legacy_6433b093",
    "vehicle_plate_number": "11H00817"
  },
  {
    "_firebase_id": "mjyf8xe3-0o94lak3rsm",
    "boarding_permit_by": "mjvoehos-xfb84bnjfw",
    "boarding_permit_by_name": "Lan Anh",
    "boarding_permit_time": "2026-01-03T22:34:49+07:00",
    "created_at": "2026-01-03T14:52:15.243Z",
    "current_status": "permit_issued",
    "entry_by": "mjvoehos-xfb84bnjfw",
    "entry_by_name": "Lan Anh",
    "entry_shift_id": "mjbgk8rq-v4u2c6zkn2k",
    "entry_time": "2026-01-03T21:51:58.693Z",
    "id": "mjyf8xe3-0o94lak3rsm",
    "passenger_drop_by": "mjvoehos-xfb84bnjfw",
    "passenger_drop_by_name": "Lan Anh",
    "passenger_drop_time": "2026-01-03T21:52:15+07:00",
    "passengers_arrived": 12,
    "permit_shift_id": "mjbgk8rq-197glyortqd",
    "permit_status": "approved",
    "planned_departure_time": "2026-01-03T15:37:00.000Z",
    "route_id": "0124_1120_A",
    "route_name": " - ",
    "route_type": "fixed",
    "seat_count": 12,
    "transport_order_code": "LENH009",
    "updated_at": "2026-01-03T15:34:49.363Z",
    "vehicle_id": "legacy_fb41de5e",
    "vehicle_plate_number": "14H05096"
  },
  {
    "_firebase_id": "mjygb2m9-mq7n6qg9b3m",
    "boarding_permit_by": "mjvoehos-xfb84bnjfw",
    "boarding_permit_by_name": "Lan Anh",
    "boarding_permit_time": "2026-01-03T22:34:15+07:00",
    "created_at": "2026-01-03T15:21:54.945Z",
    "current_status": "permit_issued",
    "entry_by": "mjvoehos-xfb84bnjfw",
    "entry_by_name": "Lan Anh",
    "entry_shift_id": "mjbgk8rq-197glyortqd",
    "entry_time": "2026-01-03T22:21:43.769Z",
    "id": "mjygb2m9-mq7n6qg9b3m",
    "passenger_drop_by": "mjvoehos-xfb84bnjfw",
    "passenger_drop_by_name": "Lan Anh",
    "passenger_drop_time": "2026-01-03T22:21:55+07:00",
    "passengers_arrived": 12,
    "permit_shift_id": "mjbgk8rq-197glyortqd",
    "permit_status": "approved",
    "planned_departure_time": "2026-01-03T15:35:00.000Z",
    "route_id": "0124_1120_A",
    "route_name": " - ",
    "route_type": "fixed",
    "seat_count": 28,
    "transport_order_code": "LENH009",
    "updated_at": "2026-01-03T15:34:16.023Z",
    "vehicle_id": "legacy_46349715",
    "vehicle_plate_number": "19H10347"
  },
  {
    "_firebase_id": "mjygnlrt-ksd40e9ff7s",
    "created_at": "2026-01-03T15:31:39.641Z",
    "current_status": "cancelled",
    "driver_full_name": "",
    "entry_by": "mjvoehos-xfb84bnjfw",
    "entry_by_name": "Lan Anh",
    "entry_shift_id": "mjbgk8rq-197glyortqd",
    "entry_time": "2026-01-03T22:31:29.915Z",
    "id": "mjygnlrt-ksd40e9ff7s",
    "metadata": {
      "cancellation_reason": "Hủy bởi người dùng từ màn hình điều độ",
      "cancelled_at": "2026-01-03T15:32:15.318Z",
      "cancelled_by": "mjvoehos-xfb84bnjfw",
      "cancelled_by_name": "Lan Anh",
      "previous_status": "passengers_dropped"
    },
    "passenger_drop_by": "mjvoehos-xfb84bnjfw",
    "passenger_drop_by_name": "Lan Anh",
    "passenger_drop_time": "2026-01-03T22:31:39+07:00",
    "passengers_arrived": 12,
    "route_id": "0124_1120_A",
    "route_name": " - ",
    "route_type": "fixed",
    "updated_at": "2026-01-03T15:32:15.319Z",
    "vehicle_id": "legacy_3856f2d7",
    "vehicle_plate_number": "22B00637"
  },
  {
    "_firebase_id": "mjygon45-1s3yy0mxlt5",
    "boarding_permit_by": "mjvoehos-xfb84bnjfw",
    "boarding_permit_by_name": "Lan Anh",
    "boarding_permit_time": "2026-01-03T22:32:46+07:00",
    "created_at": "2026-01-03T15:32:28.037Z",
    "current_status": "permit_issued",
    "entry_by": "mjvoehos-xfb84bnjfw",
    "entry_by_name": "Lan Anh",
    "entry_shift_id": "mjbgk8rq-197glyortqd",
    "entry_time": "2026-01-03T22:32:16.791Z",
    "id": "mjygon45-1s3yy0mxlt5",
    "passenger_drop_by": "mjvoehos-xfb84bnjfw",
    "passenger_drop_by_name": "Lan Anh",
    "passenger_drop_time": "2026-01-03T22:32:28+07:00",
    "passengers_arrived": 12,
    "permit_shift_id": "mjbgk8rq-197glyortqd",
    "permit_status": "approved",
    "planned_departure_time": "2026-01-03T15:34:00.000Z",
    "route_id": "0124_1316_A",
    "route_name": " - ",
    "route_type": "fixed",
    "seat_count": 12,
    "transport_order_code": "CPNT",
    "updated_at": "2026-01-03T15:32:46.142Z",
    "vehicle_id": "legacy_878eafc2",
    "vehicle_plate_number": "11H00854"
  },
  {
    "_firebase_id": "mjygtuze-797d6yxhq9w",
    "created_at": "2026-01-03T15:36:31.514Z",
    "current_status": "passengers_dropped",
    "driver_full_name": "",
    "entry_by": "mjvoehos-xfb84bnjfw",
    "entry_by_name": "Lan Anh",
    "entry_shift_id": "mjbgk8rq-197glyortqd",
    "entry_time": "2026-01-03T22:36:14.438Z",
    "id": "mjygtuze-797d6yxhq9w",
    "passenger_drop_by": "mjvoehos-xfb84bnjfw",
    "passenger_drop_by_name": "Lan Anh",
    "passenger_drop_time": "2026-01-03T22:36:31+07:00",
    "passengers_arrived": 12,
    "route_id": "0124_1213_A",
    "route_name": " - ",
    "route_type": "fixed",
    "updated_at": "2026-01-03T15:36:31.914Z",
    "vehicle_id": "legacy_3856f2d7",
    "vehicle_plate_number": "22B00637"
  },
  {
    "_firebase_id": "mjygv6l5-xf19czpnui",
    "created_at": "2026-01-03T15:37:33.209Z",
    "current_status": "passengers_dropped",
    "driver_full_name": "",
    "entry_by": "mjvoehos-xfb84bnjfw",
    "entry_by_name": "Lan Anh",
    "entry_shift_id": "mjbgk8rq-197glyortqd",
    "entry_time": "2026-01-03T22:37:19.608Z",
    "id": "mjygv6l5-xf19czpnui",
    "passenger_drop_by": "mjvoehos-xfb84bnjfw",
    "passenger_drop_by_name": "Lan Anh",
    "passenger_drop_time": "2026-01-03T22:37:33+07:00",
    "passengers_arrived": 12,
    "route_id": "0124_1123_A",
    "route_name": " - ",
    "route_type": "fixed",
    "updated_at": "2026-01-03T15:37:33.590Z",
    "vehicle_id": "legacy_434c64c3",
    "vehicle_plate_number": "22F00152"
  },
  {
    "_firebase_id": "mjyhc7zs-acgaxmlqag",
    "created_at": "2026-01-03T15:50:48.184Z",
    "current_status": "passengers_dropped",
    "driver_full_name": "",
    "entry_by": "mjvoehos-xfb84bnjfw",
    "entry_by_name": "Lan Anh",
    "entry_shift_id": "mjbgk8rq-197glyortqd",
    "entry_time": "2026-01-03T22:50:35.908Z",
    "id": "mjyhc7zs-acgaxmlqag",
    "passenger_drop_by": "mjvoehos-xfb84bnjfw",
    "passenger_drop_by_name": "Lan Anh",
    "passenger_drop_time": "2026-01-03T22:50:48+07:00",
    "passengers_arrived": 12,
    "route_id": "0124_1123_A",
    "route_name": " - ",
    "route_type": "fixed",
    "updated_at": "2026-01-03T15:50:48.563Z",
    "vehicle_id": "legacy_014cdca5",
    "vehicle_plate_number": "11E00256"
  },
  {
    "_firebase_id": "mjynumh6-jarwdagtgt",
    "created_at": "2026-01-03T18:53:04.458Z",
    "current_status": "passengers_dropped",
    "driver_full_name": "",
    "entry_by": "mjvoehos-xfb84bnjfw",
    "entry_by_name": "Lan Anh",
    "entry_shift_id": "mjbgk8rq-197glyortqd",
    "entry_time": "2026-01-04T01:52:48.485Z",
    "id": "mjynumh6-jarwdagtgt",
    "passenger_drop_by": "mjvoehos-xfb84bnjfw",
    "passenger_drop_by_name": "Lan Anh",
    "passenger_drop_time": "2026-01-04T01:53:04+07:00",
    "passengers_arrived": 123,
    "route_id": "0124_1120_A",
    "route_name": " - ",
    "route_type": "fixed",
    "updated_at": "2026-01-03T18:53:04.916Z",
    "vehicle_id": "11H00803",
    "vehicle_plate_number": ""
  }
]